[
  {
    "grade": 2014,
    "data": [
      {
        "id": 12,
        "name": "新网站上线",
        "img": "ALkp98b_mQ3MzkP.png",
        "description": "开拓信息科学与工程学院网站，成功上线运行"
      }
    ]
  },
  {
    "grade": 2015,
    "data": [
      {
        "id": 10,
        "name": "新网站上线",
        "img": "国际极地与海洋门户.png",
        "description": "中国海洋大学海洋技术系网站成功上线运行"
      },
      {
        "id": 11,
        "name": "制作展示页",
        "img": "iGEM.png",
        "description": "为中国海洋大学iGEM比赛团队制作静态展示页面"
      }
    ]
  },
  {
    "grade": 2016,
    "data": [
      {
        "id": 8,
        "name": "上线教育网站",
        "img": "Fm2pUJJ_9QZ4h3l.png",
        "description": "爱特为中国海洋大学国际教育学院制作的新版展示网上线运行"
      },
      {
        "id": 9,
        "name": "上线网站",
        "img": "",
        "description": "由爱特制作的中国海洋大学计算机系网站成功上线"
      }
    ]
  },
  {
    "grade": 2017,
    "data": [
      {
        "id": 7,
        "name": "开拓信院网站",
        "img": "itxx.jpeg",
        "description": "开拓信息科学与工程学院网站，成功上线运行"
      }
    ]
  },
  {
    "grade": 2018,
    "data": [
      {
        "id": 5,
        "name": "开拓展示网",
        "img": "",
        "description": "开拓爱特展示网，成功上线运行"
      },
      {
        "id": 6,
        "name": "新网站上线",
        "img": "",
        "description": "制作众创空间预约系统，成功上线运行"
      }
    ]
  },
  {
    "grade": 2019,
    "data": [
      {
        "id": 3,
        "name": "作品展示",
        "img": "dlbb.png",
        "description": "19年游戏部合作完成了一个可联网、能存档的俯视角射击游戏。"
      },
      {
        "id": 4,
        "name": "部门合作作品",
        "img": "",
        "description": "Ul与web开发、APP、程序合作。设计了爱特读书及爱特读书APP、爱特展示网、IT日程APP。"
      }
    ]
  },
  {
    "grade": 2020,
    "data": [
      {
        "id": 1,
        "name": "作品展示",
        "img": "",
        "description": "游戏部门独立完成了一款PC端的2.5D游戏《幽灵骑士》。"
      },
      {
        "id": 2,
        "name": "作品展示",
        "img": "",
        "description": "程序、APP与UI合作完成了爱特展示网、海迅APP等作品。"
      }
    ]
  },
  {
    "grade": 2021,
    "data": [
      {
        "id": 13,
        "name": "校团委网站",
        "img": "校团委.png",
        "description": "由爱特制作的中国海洋大学网站成功上线运行"
      }
    ]
  },
  {
    "grade": 2022,
    "data": [
      {
        "id": 16,
        "name": "制作新游戏",
        "img": "大地之歌.png",
        "description": "游戏部门独立完成一款横板闯关类游戏《大地之歌》"
      },
      {
        "id": 17,
        "name": "莱博电商平台",
        "img": "LAIBO.png",
        "description": "由爱特成员为校友企业制作电商购物网站"
      },
      {
        "id": 18,
        "name": "工程学院网站",
        "img": "中英海洋能研究基地.png",
        "description": "为工程学院中英海洋能研究基地制作展示网站"
      },
      {
        "id": 19,
        "name": "物联网数据平台",
        "img": "物联网.png",
        "description": "为校外企业制作物联网数据实时展示平台"
      }
    ]
  }
]
